pylox/__init__.py
pylox/__main__.py
pylox/scanner.py
pylox/token.py
pylox/tokentype.py
pylox-0.0.1.dist-info/DESCRIPTION.rst
pylox-0.0.1.dist-info/METADATA
pylox-0.0.1.dist-info/RECORD
pylox-0.0.1.dist-info/WHEEL
pylox-0.0.1.dist-info/entry_points.txt
pylox-0.0.1.dist-info/metadata.json
pylox-0.0.1.dist-info/top_level.txt
