Metadata-Version: 2.0
Name: pylox
Version: 0.0.1
Summary: Python implementation of Lox programming language
Home-page: https://github.com/selectnull/pylox
Author: Sasha Matijasic
Author-email: sasha@selectnull.com
License: MIT
Platform: UNKNOWN
Classifier: Development Status :: 2 - Pre-Alpha
Classifier: Environment :: Console
Classifier: Intended Audience :: Developers
Classifier: License :: OSI Approved :: MIT License
Classifier: Environment :: Console
Classifier: Programming Language :: Python
Classifier: Programming Language :: Python :: 3
Classifier: Programming Language :: Python :: 3.6
Classifier: Programming Language :: Python :: 3 :: Only
